auto_zorder/__init__.py
auto_zorder/main.py
auto_zorder-0.1.1.dist-info/LICENSE
auto_zorder-0.1.1.dist-info/METADATA
auto_zorder-0.1.1.dist-info/WHEEL
auto_zorder-0.1.1.dist-info/top_level.txt
auto_zorder-0.1.1.dist-info/RECORD
