Metadata-Version: 2.1
Name: auto-zorder
Version: 0.1.1
Summary: The project aims to remove the guesswork of selecting columns to be used in the ZORDER statement. It achieves this by analyzing the logged execution plan for each cluster provided and returns the top n columns that were used in filter/where clauses.
Author: Michael Gardner
Author-email: gardnmi@gmail.com
License: UNKNOWN
Keywords: python,databricks,delta,spark
Platform: UNKNOWN
Classifier: Development Status :: 5 - Production/Stable
Classifier: Intended Audience :: Developers
Classifier: Programming Language :: Python :: 3
Classifier: Operating System :: Unix
Classifier: Operating System :: MacOS :: MacOS X
Classifier: Operating System :: Microsoft :: Windows
License-File: LICENSE
